{"lTa9LIWtMsKLtfGdJQmXMA==":"the_stone_lust%20background-2000x1332.png","jn3yem/8XUiwyAfTdUP2+w==":"the%20stone%20lust%20lineup-2000x1333.png","gvBlP0AKWb1JBRKhYW8wWQ==":"the_stone_lust_footer-2000x1332.png","jtpL8keNFqop6RNjxBIHcw==":"the_stone_lust_footer-2000x1332.jpg","FmMJWIPIloXZQ9nx2Q/0JA==":"the_stone_lust_footer-1-2000x1332.jpg","6Sc6x1BoRR/hENwldRzzkA==":"the_stone_lust_footer-2-2000x1332.jpg","fSwdNX6bDrZFKgb+v0TXvQ==":"the_stone_lust_footer-3-2000x1332.jpg","ouMnj0jKowMnElSceC8eJQ==":"the_stone_lust_footer-4-2000x1332.jpg","FfALrBhlAiB8wUtRXrA2tw==":"lineup_full-122x81.jpg","hv1nsqsQgyp+g5hBT77R7Q==":"lineup_full-184x123.jpg","/p7zjGiOZik+saodFfLVkQ==":"the_stone_lust_footer-5-2000x1332.jpg","UTVFvvXC585qBuK1YdklsA==":"the_stone_lust%20background-2000x1332.png","LYEUTIsLOelvUNidGWM3Gw==":"the_stone_lust_footer-6-2000x1332.jpg"}